{"build": "py_0", "build_number": 0, "depends": ["anyqt >=0.0.6", "colorcet", "extranormal3 >=0.0.3", "h5py", "orange3 >=3.24", "pyqtgraph >=0.10.0", "python", "scipy >=0.14.0", "serverfiles >=0.2", "spectral >=0.18"], "license": "GPL-3", "license_family": "GPL", "name": "orange-spectroscopy", "noarch": "python", "subdir": "noarch", "timestamp": 1589466661859, "version": "0.5.3", "size": 2723342, "md5": "2c20c410210a67aee369a5ad295a4506", "sha256": "151dee1e8f25a305d01c3a7d13ed1de024cb7d73089f9e8a93b557b673b723e6"}